OBP_reliability_pillar/__init__.py
OBP_reliability_pillar/auto_scaling/__init__.py
OBP_reliability_pillar/auto_scaling/asg_elb_healthcheck_required.py
OBP_reliability_pillar/auto_scaling/compliance.py
OBP_reliability_pillar/auto_scaling/launch_config_public_ip_disabled.py
OBP_reliability_pillar/cloudwatch/__init__.py
OBP_reliability_pillar/cloudwatch/alarm_action_check.py
OBP_reliability_pillar/cloudwatch/compliance.py
OBP_reliability_pillar/dynamodb/__init__.py
OBP_reliability_pillar/dynamodb/compliance.py
OBP_reliability_pillar/dynamodb/dynamodb_autoscaling_enabled.py
OBP_reliability_pillar/dynamodb/dynamodb_pitr_enabled.py
OBP_reliability_pillar/dynamodb/utils.py
OBP_reliability_pillar/ec2/__init__.py
OBP_reliability_pillar/ec2/compliance.py
OBP_reliability_pillar/ec2/ec2_instance_detailed_monitoring_enabled.py
OBP_reliability_pillar/ec2/instance_in_vpc.py
OBP_reliability_pillar/elastic_beanstalk/__init__.py
OBP_reliability_pillar/elastic_beanstalk/compliance.py
OBP_reliability_pillar/elastic_beanstalk/enhanced_health_reporting_enabled.py
OBP_reliability_pillar/elastic_load_balancer/__init__.py
OBP_reliability_pillar/elastic_load_balancer/compliance.py
OBP_reliability_pillar/elastic_load_balancer/cross_zone_load_balancing_enabled.py
OBP_reliability_pillar/elastic_load_balancer/elb_deletion_protection.py
OBP_reliability_pillar/elastic_load_balancer/utils.py
OBP_reliability_pillar/elastic_search/__init__.py
OBP_reliability_pillar/elastic_search/compliance.py
OBP_reliability_pillar/elastic_search/elastic_search_in_vpc_only.py
OBP_reliability_pillar/guard_duty/__init__.py
OBP_reliability_pillar/guard_duty/compliance.py
OBP_reliability_pillar/guard_duty/guard_duty_enabled.py
OBP_reliability_pillar/lambdafn/__init__.py
OBP_reliability_pillar/lambdafn/compliance.py
OBP_reliability_pillar/lambdafn/lambda_dlq_check.py
OBP_reliability_pillar/lambdafn/lambda_inside_vpc.py
OBP_reliability_pillar/lambdafn/utils.py
OBP_reliability_pillar/rds/__init__.py
OBP_reliability_pillar-0.2.0.dist-info/LICENCE
OBP_reliability_pillar-0.2.0.dist-info/METADATA
OBP_reliability_pillar-0.2.0.dist-info/WHEEL
OBP_reliability_pillar-0.2.0.dist-info/top_level.txt
OBP_reliability_pillar-0.2.0.dist-info/RECORD
